README.rst
setup.py
data/helloworld_demo.pdf
data/helloworld_demo.png
xmisc/__init__.py
xmisc.egg-info/PKG-INFO
xmisc.egg-info/SOURCES.txt
xmisc.egg-info/__init__.py
xmisc.egg-info/dependency_links.txt
xmisc.egg-info/requires.txt
xmisc.egg-info/top_level.txt
xmisc/graphics/__init__.py
xmisc/graphics/axes3d_import.py
xmisc/graphics/bar3d.py
xmisc/graphics/helloworld.py
xmisc/graphics/lego.py
xmisc/graphics/pie.py
xmisc/utils/__init__.py
xmisc/utils/dataframe.py
xmisc/utils/file.py
xmisc/utils/list.py
xmisc/utils/logging.py