Metadata-Version: 1.0
Name: xmisc
Version: 0.1.6
Summary: Xiaobei's miscellaneous classes and functions
Home-page: https://github.com/xiaobeizhao/xmiscpy
Author: Xiaobei Zhao
Author-email: xiaobei_zhao(at)med.unc.edu
License: GNU LGPL
Platform: UNKNOWN
